toady/__init__.py
toady/cli.py
toady/command_utils.py
toady/error_handling.py
toady/exceptions.py
toady/py.typed
toady/utils.py
toady/commands/__init__.py
toady/commands/fetch.py
toady/commands/reply.py
toady/commands/resolve.py
toady/commands/schema.py
toady/formatters/__init__.py
toady/formatters/format_interfaces.py
toady/formatters/format_selection.py
toady/formatters/formatters.py
toady/formatters/json_formatter.py
toady/formatters/pretty_formatter.py
toady/models/__init__.py
toady/models/models.py
toady/parsers/__init__.py
toady/parsers/graphql_parser.py
toady/parsers/graphql_queries.py
toady/parsers/parsers.py
toady/services/__init__.py
toady/services/fetch_service.py
toady/services/github_service.py
toady/services/pr_selection.py
toady/services/pr_selector.py
toady/services/reply_service.py
toady/services/resolve_service.py
toady/validators/__init__.py
toady/validators/node_id_validation.py
toady/validators/schema_validator.py
toady/validators/validation.py
toady_cli-0.1.0.dist-info/licenses/LICENSE
toady_cli-0.1.0.dist-info/METADATA
toady_cli-0.1.0.dist-info/WHEEL
toady_cli-0.1.0.dist-info/entry_points.txt
toady_cli-0.1.0.dist-info/top_level.txt
toady_cli-0.1.0.dist-info/RECORD
