Metadata-Version: 2.4
Name: toady-cli
Version: 0.1.0
Summary: A CLI tool for managing GitHub PR code reviews efficiently
Author-email: Tony Blank <guillotine@lawnfucker.com>
Maintainer-email: Tony Blank <guillotine@lawnfucker.com>
License-Expression: MIT
Project-URL: Homepage, https://github.com/tonyblank/toady-cli
Project-URL: Documentation, https://github.com/tonyblank/toady-cli#readme
Project-URL: Repository, https://github.com/tonyblank/toady-cli.git
Project-URL: Bug Tracker, https://github.com/tonyblank/toady-cli/issues
Keywords: github,cli,code-review,pull-request,automation
Classifier: Development Status :: 3 - Alpha
Classifier: Intended Audience :: Developers
Classifier: Operating System :: OS Independent
Classifier: Programming Language :: Python :: 3
Classifier: Programming Language :: Python :: 3.9
Classifier: Programming Language :: Python :: 3.10
Classifier: Programming Language :: Python :: 3.11
Classifier: Programming Language :: Python :: 3.12
Classifier: Topic :: Software Development :: Version Control :: Git
Classifier: Topic :: Software Development :: Quality Assurance
Classifier: Environment :: Console
Requires-Python: >=3.9
License-File: LICENSE
Requires-Dist: click>=8.1.7
Requires-Dist: rich>=13.9.0
Requires-Dist: rich-click>=1.8.0
Requires-Dist: typing-extensions>=4.12.0; python_version < "3.11"
Provides-Extra: dev
Requires-Dist: pytest>=8.3.0; extra == "dev"
Requires-Dist: pytest-cov>=6.0.0; extra == "dev"
Requires-Dist: pytest-mock>=3.14.0; extra == "dev"
Requires-Dist: pytest-xdist>=3.6.0; extra == "dev"
Requires-Dist: pytest-timeout>=2.3.1; extra == "dev"
Requires-Dist: black>=24.8.0; extra == "dev"
Requires-Dist: ruff>=0.8.0; extra == "dev"
Requires-Dist: mypy>=1.13.0; extra == "dev"
Requires-Dist: pre-commit>=4.0.0; extra == "dev"
Requires-Dist: types-click>=7.1.8; extra == "dev"
Requires-Dist: types-psutil>=6.1.0; extra == "dev"
Requires-Dist: build>=1.2.0; extra == "dev"
Requires-Dist: twine>=6.0.0; extra == "dev"
Requires-Dist: python-dotenv>=1.0.1; extra == "dev"
Requires-Dist: psutil>=6.1.0; extra == "dev"
Requires-Dist: mkdocs>=1.6.0; extra == "dev"
Requires-Dist: mkdocs-material>=9.5.0; extra == "dev"
Provides-Extra: test
Requires-Dist: pytest>=8.3.0; extra == "test"
Requires-Dist: pytest-cov>=6.0.0; extra == "test"
Requires-Dist: pytest-mock>=3.14.0; extra == "test"
Requires-Dist: pytest-xdist>=3.6.0; extra == "test"
Requires-Dist: python-dotenv>=1.0.1; extra == "test"
Provides-Extra: docs
Requires-Dist: mkdocs>=1.6.0; extra == "docs"
Requires-Dist: mkdocs-material>=9.5.0; extra == "docs"
Requires-Dist: mkdocs-click>=0.8.1; extra == "docs"
Dynamic: license-file
